pybtreecore/__init__.py
pybtreecore/btcore.py
pybtreecore/btnode.py
pybtreecore/btnodelist.py
pybtreecore/conv.py
pybtreecore/hexdump.py
pybtreecore-0.0.6.dist-info/LICENSE.md
pybtreecore-0.0.6.dist-info/METADATA
pybtreecore-0.0.6.dist-info/WHEEL
pybtreecore-0.0.6.dist-info/top_level.txt
pybtreecore-0.0.6.dist-info/RECORD
