Metadata-Version: 2.1
Name: pybtreecore
Version: 0.0.6
Summary: pybtreecore - python implementation of core B-Tree methods storage memory management
Home-page: https://github.com/kr-g/pybtreecore
Author: k.r. goger
Author-email: k.r.goger+pybtreecore@gmail.com
License: UNKNOWN
Keywords: implementation of core B-Tree methods storage memory management pyheapfile
Platform: UNKNOWN
Classifier: Development Status :: 3 - Alpha
Classifier: Operating System :: POSIX :: Linux
Classifier: Intended Audience :: Developers
Classifier: Programming Language :: Python :: 3
Classifier: License :: OSI Approved :: GNU Affero General Public License v3 or later (AGPLv3+)
Requires-Python: >=3.6
Requires-Dist: pydllfile
Requires-Dist: pyheapfile
